CHANGELOG
COPYING
MANIFEST.in
README
setup.py
docs/make_docs.py
docs/templates/base.html
docs/templates/class.html
docs/templates/module.html
examples/COPYING
examples/button.png
examples/button2.png
examples/button_wide.png
examples/example.py
examples/icon.png
examples/icon2.png
examples/scrollbar.png
examples/scrollblock.png
examples/scrollbox.png
snowui/__init__.py
snowui/button.py
snowui/main.py
snowui/scrollbox.py
snowui/text.py
snowui/widget.py
snowui.egg-info/PKG-INFO
snowui.egg-info/SOURCES.txt
snowui.egg-info/dependency_links.txt
snowui.egg-info/top_level.txt