Metadata-Version: 1.0
Name: snowui
Version: 0.1.1
Summary: snowui is a fast and simple GUI using pyglet and rabbyt.
Home-page: http://joey101.net/snowui/
Author: Joey Marshall
Author-email: joey@joey101.net
License: MIT
Platform: UNKNOWN
